{"DocumentConnection":{"type":"DocumentConnection","resolveType":"multiCollectionDocumentList","collections":["article","project","resource"]},"Node":{"type":"Node","resolveType":"nodeDocument"},"DocumentNode":{"type":"DocumentNode","resolveType":"multiCollectionDocument","createDocument":"create","updateDocument":"update"},"Article":{"type":"Article","resolveType":"collectionDocument","collection":"article","createArticle":"create","updateArticle":"update"},"ArticleConnection":{"type":"ArticleConnection","resolveType":"collectionDocumentList","collection":"article"},"Project":{"type":"Project","resolveType":"collectionDocument","collection":"project","createProject":"create","updateProject":"update"},"ProjectConnection":{"type":"ProjectConnection","resolveType":"collectionDocumentList","collection":"project"},"Resource":{"type":"Resource","resolveType":"collectionDocument","collection":"resource","createResource":"create","updateResource":"update"},"ResourceConnection":{"type":"ResourceConnection","resolveType":"collectionDocumentList","collection":"resource"}}